CsForAll/README.md
CsForAll/__init__.py
CsForAll/__main__.py
CsForAll/file.epub
CsForAll/index.html
CsForAll/css/__init__.py
CsForAll/css/annotations.css
CsForAll/css/main.css
CsForAll/css/normalize.css
CsForAll/css/popup.css
CsForAll/font/__init__.py
CsForAll/font/fontello.eot
CsForAll/font/fontello.svg
CsForAll/font/fontello.ttf
CsForAll/font/fontello.woff
CsForAll/img/__init__.py
CsForAll/img/annotator-glyph-sprite.png
CsForAll/img/annotator-icon-sprite.png
CsForAll/img/apple-touch-icon.png
CsForAll/img/cancelfullscreen.png
CsForAll/img/close.png
CsForAll/img/fullscreen.png
CsForAll/img/loader.gif
CsForAll/img/menu-icon.png
CsForAll/img/save.png
CsForAll/img/saved.png
CsForAll/img/settings-s.png
CsForAll/img/settings.png
CsForAll/img/star.png
CsForAll/js/__init__.py
CsForAll/js/epub.js
CsForAll/js/epub.min.js
CsForAll/js/epub.min.map
CsForAll/js/hooks.min.js
CsForAll/js/hooks.min.map
CsForAll/js/reader.js
CsForAll/js/reader.js.map
CsForAll/js/reader.min.js
CsForAll/js/reader.min.map
CsForAll/js/hooks/__init__.py
CsForAll/js/hooks/extensions/__init__.py
CsForAll/js/hooks/extensions/highlight.js
CsForAll/js/libs/__init__.py
CsForAll/js/libs/jquery.min.js
CsForAll/js/libs/localforage.min.js
CsForAll/js/libs/screenfull.js
CsForAll/js/libs/screenfull.min.js
CsForAll/js/libs/zip.min.js
CsForAll/js/plugins/__init__.py
CsForAll/js/plugins/hypothesis.js
CsForAll/js/plugins/search.js
cs_for_all-2024.3.2.0.dist-info/METADATA
cs_for_all-2024.3.2.0.dist-info/WHEEL
cs_for_all-2024.3.2.0.dist-info/entry_points.txt
cs_for_all-2024.3.2.0.dist-info/top_level.txt
cs_for_all-2024.3.2.0.dist-info/RECORD
